MANIFEST.in
README.rst
setup.cfg
setup.py
src/rating/__init__.py
src/rating/models.py
src/rating/urls.py
src/rating/views.py
src/rating/media/css/crystal-stars.css
src/rating/media/css/jquery.ui.stars.css
src/rating/media/images/stars/crystal-arrows.gif
src/rating/media/images/stars/crystal-stars.png
src/rating/media/images/stars/crystal-stars_.png
src/rating/media/images/stars/jquery.ui.stars.gif
src/rating/media/js/jquery.ui.core.js
src/rating/media/js/jquery.ui.stars.js
src/rating/media/js/jquery.ui.stars.min.js
src/rating/media/js/jquery.ui.widget.js
src/rating/media/js/stars.js
src/rating/templates/stars.html
src/rating/templatetags/__init__.py
src/rating/templatetags/stars.py
src/stars_rating.egg-info/PKG-INFO
src/stars_rating.egg-info/SOURCES.txt
src/stars_rating.egg-info/dependency_links.txt
src/stars_rating.egg-info/not-zip-safe
src/stars_rating.egg-info/requires.txt
src/stars_rating.egg-info/top_level.txt