Metadata-Version: 1.1
Name: stars-rating
Version: 0.1
Summary: Django application to rate objects & stars UI
Home-page: http://github.com/Arpaso/stars-rating
Author: Arpaso
Author-email: arvid@arpaso.com
License: UNKNOWN
Download-URL: http://github.com/Arpaso/stars-rating/tarball/0.1
Platform: UNKNOWN
Classifier: Development Status :: 4 - Beta
Classifier: Framework :: Django
Classifier: Intended Audience :: Developers
Classifier: Intended Audience :: System Administrators
Classifier: Operating System :: OS Independent
Classifier: Topic :: Software Development
